{
  "project_info": {
    "project_number": "150774034680",
    "firebase_url": "https://mystargram-c11e7.firebaseio.com",
    "project_id": "mystargram-c11e7",
    "storage_bucket": "mystargram-c11e7.appspot.com"
  },
  "client": [
    {
      "client_info": {
        "mobilesdk_app_id": "1:150774034680:android:7f6eb83d9fc4bcc0b14b0d",
        "android_client_info": {
          "package_name": "com.example.mystar"
        }
      },
      "oauth_client": [
        {
          "client_id": "150774034680-riv85dckemr6e33n7t0k8q5e3njnijdm.apps.googleusercontent.com",
          "client_type": 3
        }
      ],
      "api_key": [
        {
          "current_key": "AIzaSyCGmE6qELb1GBy67PmXftqI1LRhYVzEurs"
        }
      ],
      "services": {
        "appinvite_service": {
          "other_platform_oauth_client": [
            {
              "client_id": "150774034680-riv85dckemr6e33n7t0k8q5e3njnijdm.apps.googleusercontent.com",
              "client_type": 3
            }
          ]
        }
      }
    },
    {
      "client_info": {
        "mobilesdk_app_id": "1:150774034680:android:a278f4fabf3bf7f4b14b0d",
        "android_client_info": {
          "package_name": "com.example.mystargram"
        }
      },
      "oauth_client": [
        {
          "client_id": "150774034680-riv85dckemr6e33n7t0k8q5e3njnijdm.apps.googleusercontent.com",
          "client_type": 3
        }
      ],
      "api_key": [
        {
          "current_key": "AIzaSyCGmE6qELb1GBy67PmXftqI1LRhYVzEurs"
        }
      ],
      "services": {
        "appinvite_service": {
          "other_platform_oauth_client": [
            {
              "client_id": "150774034680-riv85dckemr6e33n7t0k8q5e3njnijdm.apps.googleusercontent.com",
              "client_type": 3
            }
          ]
        }
      }
    }
  ],
  "configuration_version": "1"
}